{  "version" :"2.0",  "name" :"m2_system_impl_Instance",  "category" :"system",  "featureInstance" :[ {    "name" :"afdx_access",    "category" :"busAccess",    "feature" :{      "type" :"aadl2:BusAccess",      "href" :"../../github/AADLib/examples/fms/subsystem.aadl#/0/@ownedPublicSection/@ownedClassifier.5/@ownedBusAccess.0"    },    "type" :{      "href" :"../../github/AADLib/examples/fms/instances/subsystem_m2_system_impl_Instance.aaxl2#/6"    }  }, {    "name" :"ph_wpId1",    "category" :"eventDataPort",    "feature" :{      "type" :"aadl2:EventDataPort",      "href" :"../../github/AADLib/examples/fms/subsystem.aadl#/0/@ownedPublicSection/@ownedClassifier.5/@ownedEventDataPort.0"    },    "type" :{      "href" :"../../github/AADLib/examples/fms/instances/subsystem_m2_system_impl_Instance.aaxl2#/0"    }  }, {    "name" :"ph_answer1",    "category" :"eventDataPort",    "feature" :{      "type" :"aadl2:EventDataPort",      "href" :"../../github/AADLib/examples/fms/subsystem.aadl#/0/@ownedPublicSection/@ownedClassifier.5/@ownedEventDataPort.1"    },    "type" :{      "href" :"../../github/AADLib/examples/fms/instances/subsystem_m2_system_impl_Instance.aaxl2#/2"    }  }, {    "name" :"ph_speed1",    "category" :"eventDataPort",    "feature" :{      "type" :"aadl2:EventDataPort",      "href" :"../../github/AADLib/examples/fms/subsystem.aadl#/0/@ownedPublicSection/@ownedClassifier.5/@ownedEventDataPort.2"    },    "type" :{      "href" :"../../github/AADLib/examples/fms/instances/subsystem_m2_system_impl_Instance.aaxl2#/4"    }  }, {    "name" :"ph_query1",    "category" :"eventDataPort",    "direction" :"out",    "feature" :{      "type" :"aadl2:EventDataPort",      "href" :"../../github/AADLib/examples/fms/subsystem.aadl#/0/@ownedPublicSection/@ownedClassifier.5/@ownedEventDataPort.3"    },    "type" :{      "href" :"../../github/AADLib/examples/fms/instances/subsystem_m2_system_impl_Instance.aaxl2#/1"    }  }, {    "name" :"ph_wpInfo1",    "category" :"eventDataPort",    "direction" :"out",    "feature" :{      "type" :"aadl2:EventDataPort",      "href" :"../../github/AADLib/examples/fms/subsystem.aadl#/0/@ownedPublicSection/@ownedClassifier.5/@ownedEventDataPort.4"    },    "type" :{      "href" :"../../github/AADLib/examples/fms/instances/subsystem_m2_system_impl_Instance.aaxl2#/3"    }  }, {    "name" :"ph_ETA1",    "category" :"eventDataPort",    "direction" :"out",    "feature" :{      "type" :"aadl2:EventDataPort",      "href" :"../../github/AADLib/examples/fms/subsystem.aadl#/0/@ownedPublicSection/@ownedClassifier.5/@ownedEventDataPort.5"    },    "type" :{      "href" :"../../github/AADLib/examples/fms/instances/subsystem_m2_system_impl_Instance.aaxl2#/5"    }  } ],  "componentInstance" :[ {    "name" :"mainmemory",    "category" :"memory",    "componentInstance" :{      "name" :"mem_fm1",      "category" :"memory",      "subcomponent" :{        "type" :"aadl2:MemorySubcomponent",        "href" :"../../github/AADLib/examples/fms/fms_hardware.aadl#/0/@ownedPublicSection/@ownedClassifier.20/@ownedMemorySubcomponent.0"      },      "index" :"0",      "classifier" :{        "type" :"aadl2:MemoryType",        "href" :"../../github/AADLib/examples/fms/fms_hardware.aadl#fms_hardware.memchunk"      }    },    "subcomponent" :{      "type" :"aadl2:MemorySubcomponent",      "href" :"../../github/AADLib/examples/fms/subsystem.aadl#/0/@ownedPublicSection/@ownedClassifier.6/@ownedMemorySubcomponent.0"    },    "index" :"0",    "classifier" :{      "type" :"aadl2:MemoryImplementation",      "href" :"../../github/AADLib/examples/fms/fms_hardware.aadl#fms_hardware.mainmemory.m2"    }  }, {    "name" :"fm1",    "category" :"process",    "featureInstance" :[ {      "name" :"wpId1_apex",      "category" :"eventDataPort",      "feature" :{        "type" :"aadl2:EventDataPort",        "href" :"../../github/AADLib/examples/fms/m2_software.aadl#/0/@ownedPublicSection/@ownedClassifier.0/@ownedEventDataPort.0"      },      "type" :{        "href" :"../../github/AADLib/examples/fms/instances/subsystem_m2_system_impl_Instance.aaxl2#/0"      }    }, {      "name" :"query1_apex",      "category" :"eventDataPort",      "direction" :"out",      "feature" :{        "type" :"aadl2:EventDataPort",        "href" :"../../github/AADLib/examples/fms/m2_software.aadl#/0/@ownedPublicSection/@ownedClassifier.0/@ownedEventDataPort.1"      },      "type" :{        "href" :"../../github/AADLib/examples/fms/instances/subsystem_m2_system_impl_Instance.aaxl2#/1"      }    }, {      "name" :"answer1_apex",      "category" :"eventDataPort",      "feature" :{        "type" :"aadl2:EventDataPort",        "href" :"../../github/AADLib/examples/fms/m2_software.aadl#/0/@ownedPublicSection/@ownedClassifier.0/@ownedEventDataPort.2"      },      "type" :{        "href" :"../../github/AADLib/examples/fms/instances/subsystem_m2_system_impl_Instance.aaxl2#/2"      }    }, {      "name" :"wpInfo1_apex",      "category" :"eventDataPort",      "direction" :"out",      "feature" :{        "type" :"aadl2:EventDataPort",        "href" :"../../github/AADLib/examples/fms/m2_software.aadl#/0/@ownedPublicSection/@ownedClassifier.0/@ownedEventDataPort.3"      },      "type" :{        "href" :"../../github/AADLib/examples/fms/instances/subsystem_m2_system_impl_Instance.aaxl2#/3"      }    }, {      "name" :"speed1_apex",      "category" :"eventDataPort",      "feature" :{        "type" :"aadl2:EventDataPort",        "href" :"../../github/AADLib/examples/fms/m2_software.aadl#/0/@ownedPublicSection/@ownedClassifier.0/@ownedEventDataPort.4"      },      "type" :{        "href" :"../../github/AADLib/examples/fms/instances/subsystem_m2_system_impl_Instance.aaxl2#/4"      }    }, {      "name" :"ETA1_apex",      "category" :"eventDataPort",      "direction" :"out",      "feature" :{        "type" :"aadl2:EventDataPort",        "href" :"../../github/AADLib/examples/fms/m2_software.aadl#/0/@ownedPublicSection/@ownedClassifier.0/@ownedEventDataPort.5"      },      "type" :{        "href" :"../../github/AADLib/examples/fms/instances/subsystem_m2_system_impl_Instance.aaxl2#/5"      }    } ],    "componentInstance" :{      "name" :"FM1",      "category" :"thread",      "featureInstance" :[ {        "name" :"th_wpId1",        "category" :"eventDataPort",        "feature" :{          "type" :"aadl2:EventDataPort",          "href" :"../../github/AADLib/examples/fms/m2_software.aadl#/0/@ownedPublicSection/@ownedClassifier.2/@ownedEventDataPort.0"        },        "type" :{          "href" :"../../github/AADLib/examples/fms/instances/subsystem_m2_system_impl_Instance.aaxl2#/0"        }      }, {        "name" :"th_query1",        "category" :"eventDataPort",        "direction" :"out",        "feature" :{          "type" :"aadl2:EventDataPort",          "href" :"../../github/AADLib/examples/fms/m2_software.aadl#/0/@ownedPublicSection/@ownedClassifier.2/@ownedEventDataPort.1"        },        "type" :{          "href" :"../../github/AADLib/examples/fms/instances/subsystem_m2_system_impl_Instance.aaxl2#/1"        }      }, {        "name" :"th_answer1",        "category" :"eventDataPort",        "feature" :{          "type" :"aadl2:EventDataPort",          "href" :"../../github/AADLib/examples/fms/m2_software.aadl#/0/@ownedPublicSection/@ownedClassifier.2/@ownedEventDataPort.2"        },        "type" :{          "href" :"../../github/AADLib/examples/fms/instances/subsystem_m2_system_impl_Instance.aaxl2#/2"        }      }, {        "name" :"th_wpInfo1",        "category" :"eventDataPort",        "direction" :"out",        "feature" :{          "type" :"aadl2:EventDataPort",          "href" :"../../github/AADLib/examples/fms/m2_software.aadl#/0/@ownedPublicSection/@ownedClassifier.2/@ownedEventDataPort.3"        },        "type" :{          "href" :"../../github/AADLib/examples/fms/instances/subsystem_m2_system_impl_Instance.aaxl2#/3"        }      }, {        "name" :"th_speed1",        "category" :"eventDataPort",        "feature" :{          "type" :"aadl2:EventDataPort",          "href" :"../../github/AADLib/examples/fms/m2_software.aadl#/0/@ownedPublicSection/@ownedClassifier.2/@ownedEventDataPort.4"        },        "type" :{          "href" :"../../github/AADLib/examples/fms/instances/subsystem_m2_system_impl_Instance.aaxl2#/4"        }      }, {        "name" :"th_ETA1",        "category" :"eventDataPort",        "direction" :"out",        "feature" :{          "type" :"aadl2:EventDataPort",          "href" :"../../github/AADLib/examples/fms/m2_software.aadl#/0/@ownedPublicSection/@ownedClassifier.2/@ownedEventDataPort.5"        },        "type" :{          "href" :"../../github/AADLib/examples/fms/instances/subsystem_m2_system_impl_Instance.aaxl2#/5"        }      } ],      "flowSpecification" :[ {        "name" :"waypoint_query",        "source" :"//@componentInstance.1/@componentInstance.0/@featureInstance.0",        "destination" :"//@componentInstance.1/@componentInstance.0/@featureInstance.1",        "flowSpecification" :{          "href" :"../../github/AADLib/examples/fms/m2_software.aadl#/0/@ownedPublicSection/@ownedClassifier.2/@ownedFlowSpecification.0"        }      }, {        "name" :"waypoint_answer",        "source" :"//@componentInstance.1/@componentInstance.0/@featureInstance.2",        "destination" :"//@componentInstance.1/@componentInstance.0/@featureInstance.3",        "flowSpecification" :{          "href" :"../../github/AADLib/examples/fms/m2_software.aadl#/0/@ownedPublicSection/@ownedClassifier.2/@ownedFlowSpecification.1"        }      }, {        "name" :"ETA_calculation",        "source" :"//@componentInstance.1/@componentInstance.0/@featureInstance.4",        "destination" :"//@componentInstance.1/@componentInstance.0/@featureInstance.5",        "flowSpecification" :{          "href" :"../../github/AADLib/examples/fms/m2_software.aadl#/0/@ownedPublicSection/@ownedClassifier.2/@ownedFlowSpecification.2"        }      } ],      "subcomponent" :{        "type" :"aadl2:ThreadSubcomponent",        "href" :"../../github/AADLib/examples/fms/m2_software.aadl#/0/@ownedPublicSection/@ownedClassifier.1/@ownedThreadSubcomponent.0"      },      "index" :"0",      "classifier" :{        "type" :"aadl2:ThreadType",        "href" :"../../github/AADLib/examples/fms/m2_software.aadl#m2_software.th_FM1"      }    },    "flowSpecification" :[ {      "name" :"fromIdToQuery",      "source" :"//@componentInstance.1/@featureInstance.0",      "destination" :"//@componentInstance.1/@featureInstance.1",      "flowSpecification" :{        "href" :"../../github/AADLib/examples/fms/m2_software.aadl#/0/@ownedPublicSection/@ownedClassifier.0/@ownedFlowSpecification.0"      }    }, {      "name" :"fromAnswerToInfo",      "source" :"//@componentInstance.1/@featureInstance.2",      "destination" :"//@componentInstance.1/@featureInstance.3",      "flowSpecification" :{        "href" :"../../github/AADLib/examples/fms/m2_software.aadl#/0/@ownedPublicSection/@ownedClassifier.0/@ownedFlowSpecification.1"      }    }, {      "name" :"fromSpeedToETA",      "source" :"//@componentInstance.1/@featureInstance.4",      "destination" :"//@componentInstance.1/@featureInstance.5",      "flowSpecification" :{        "href" :"../../github/AADLib/examples/fms/m2_software.aadl#/0/@ownedPublicSection/@ownedClassifier.0/@ownedFlowSpecification.2"      }    } ],    "subcomponent" :{      "type" :"aadl2:ProcessSubcomponent",      "href" :"../../github/AADLib/examples/fms/subsystem.aadl#/0/@ownedPublicSection/@ownedClassifier.6/@ownedProcessSubcomponent.0"    },    "index" :"0",    "classifier" :{      "type" :"aadl2:ProcessImplementation",      "href" :"../../github/AADLib/examples/fms/m2_software.aadl#m2_software.prs_FM1.impl"    }  }, {    "name" :"cpu",    "category" :"processor",    "componentInstance" :{      "name" :"partition_FM1",      "category" :"virtual processor",      "subcomponent" :{        "type" :"aadl2:VirtualProcessorSubcomponent",        "href" :"../../github/AADLib/examples/fms/fms_hardware.aadl#/0/@ownedPublicSection/@ownedClassifier.16/@ownedVirtualProcessorSubcomponent.0"      },      "index" :"0",      "classifier" :{        "type" :"aadl2:VirtualProcessorType",        "href" :"../../github/AADLib/examples/fms/fms_hardware.aadl#fms_hardware.partition_runtime"      }    },    "subcomponent" :{      "type" :"aadl2:ProcessorSubcomponent",      "href" :"../../github/AADLib/examples/fms/subsystem.aadl#/0/@ownedPublicSection/@ownedClassifier.6/@ownedProcessorSubcomponent.0"    },    "index" :"0",    "classifier" :{      "type" :"aadl2:ProcessorImplementation",      "href" :"../../github/AADLib/examples/fms/fms_hardware.aadl#fms_hardware.arinckernel.m2"    }  } ],  "flowSpecification" :[ {    "name" :"wpId_m2_query",    "source" :"//@featureInstance.1",    "destination" :"//@featureInstance.4",    "flowSpecification" :{      "href" :"../../github/AADLib/examples/fms/subsystem.aadl#/0/@ownedPublicSection/@ownedClassifier.5/@ownedFlowSpecification.0"    }  }, {    "name" :"answer_m2_wpInfo",    "source" :"//@featureInstance.2",    "destination" :"//@featureInstance.5",    "flowSpecification" :{      "href" :"../../github/AADLib/examples/fms/subsystem.aadl#/0/@ownedPublicSection/@ownedClassifier.5/@ownedFlowSpecification.1"    }  }, {    "name" :"speed_m2_ETA",    "source" :"//@featureInstance.3",    "destination" :"//@featureInstance.6",    "flowSpecification" :{      "href" :"../../github/AADLib/examples/fms/subsystem.aadl#/0/@ownedPublicSection/@ownedClassifier.5/@ownedFlowSpecification.2"    }  }, {    "name" :"wpId_sink",    "source" :"//@featureInstance.1",    "flowSpecification" :{      "href" :"../../github/AADLib/examples/fms/subsystem.aadl#/0/@ownedPublicSection/@ownedClassifier.5/@ownedFlowSpecification.3"    }  }, {    "name" :"query_src",    "destination" :"//@featureInstance.4",    "flowSpecification" :{      "href" :"../../github/AADLib/examples/fms/subsystem.aadl#/0/@ownedPublicSection/@ownedClassifier.5/@ownedFlowSpecification.4"    }  }, {    "name" :"answer_sink",    "source" :"//@featureInstance.2",    "flowSpecification" :{      "href" :"../../github/AADLib/examples/fms/subsystem.aadl#/0/@ownedPublicSection/@ownedClassifier.5/@ownedFlowSpecification.5"    }  }, {    "name" :"wpInfo_src",    "destination" :"//@featureInstance.5",    "flowSpecification" :{      "href" :"../../github/AADLib/examples/fms/subsystem.aadl#/0/@ownedPublicSection/@ownedClassifier.5/@ownedFlowSpecification.6"    }  }, {    "name" :"speed_sink",    "source" :"//@featureInstance.3",    "flowSpecification" :{      "href" :"../../github/AADLib/examples/fms/subsystem.aadl#/0/@ownedPublicSection/@ownedClassifier.5/@ownedFlowSpecification.7"    }  } ],  "connectionInstance" :[ {    "name" :"ph_wpId1 -> fm1.FM1.th_wpId1",    "kind" :"portConnection",    "destination" :"//@componentInstance.1/@componentInstance.0/@featureInstance.0",    "source" :"//@featureInstance.1",    "connectionReference" :[ {      "context" :"/",      "source" :"//@featureInstance.1",      "destination" :"//@componentInstance.1/@featureInstance.0",      "connection" :{        "type" :"aadl2:PortConnection",        "href" :"../../github/AADLib/examples/fms/subsystem.aadl#/0/@ownedPublicSection/@ownedClassifier.6/@ownedPortConnection.0"      }    }, {      "context" :"//@componentInstance.1",      "source" :"//@componentInstance.1/@featureInstance.0",      "destination" :"//@componentInstance.1/@componentInstance.0/@featureInstance.0",      "connection" :{        "type" :"aadl2:PortConnection",        "href" :"../../github/AADLib/examples/fms/m2_software.aadl#/0/@ownedPublicSection/@ownedClassifier.1/@ownedPortConnection.0"      }    } ]  }, {    "name" :"ph_answer1 -> fm1.FM1.th_answer1",    "kind" :"portConnection",    "destination" :"//@componentInstance.1/@componentInstance.0/@featureInstance.2",    "source" :"//@featureInstance.2",    "connectionReference" :[ {      "context" :"/",      "source" :"//@featureInstance.2",      "destination" :"//@componentInstance.1/@featureInstance.2",      "connection" :{        "type" :"aadl2:PortConnection",        "href" :"../../github/AADLib/examples/fms/subsystem.aadl#/0/@ownedPublicSection/@ownedClassifier.6/@ownedPortConnection.1"      }    }, {      "context" :"//@componentInstance.1",      "source" :"//@componentInstance.1/@featureInstance.2",      "destination" :"//@componentInstance.1/@componentInstance.0/@featureInstance.2",      "connection" :{        "type" :"aadl2:PortConnection",        "href" :"../../github/AADLib/examples/fms/m2_software.aadl#/0/@ownedPublicSection/@ownedClassifier.1/@ownedPortConnection.2"      }    } ]  }, {    "name" :"ph_speed1 -> fm1.FM1.th_speed1",    "kind" :"portConnection",    "destination" :"//@componentInstance.1/@componentInstance.0/@featureInstance.4",    "source" :"//@featureInstance.3",    "connectionReference" :[ {      "context" :"/",      "source" :"//@featureInstance.3",      "destination" :"//@componentInstance.1/@featureInstance.4",      "connection" :{        "type" :"aadl2:PortConnection",        "href" :"../../github/AADLib/examples/fms/subsystem.aadl#/0/@ownedPublicSection/@ownedClassifier.6/@ownedPortConnection.2"      }    }, {      "context" :"//@componentInstance.1",      "source" :"//@componentInstance.1/@featureInstance.4",      "destination" :"//@componentInstance.1/@componentInstance.0/@featureInstance.4",      "connection" :{        "type" :"aadl2:PortConnection",        "href" :"../../github/AADLib/examples/fms/m2_software.aadl#/0/@ownedPublicSection/@ownedClassifier.1/@ownedPortConnection.4"      }    } ]  }, {    "name" :"fm1.FM1.th_query1 -> ph_query1",    "kind" :"portConnection",    "destination" :"//@featureInstance.4",    "source" :"//@componentInstance.1/@componentInstance.0/@featureInstance.1",    "connectionReference" :[ {      "context" :"//@componentInstance.1",      "source" :"//@componentInstance.1/@componentInstance.0/@featureInstance.1",      "destination" :"//@componentInstance.1/@featureInstance.1",      "connection" :{        "type" :"aadl2:PortConnection",        "href" :"../../github/AADLib/examples/fms/m2_software.aadl#/0/@ownedPublicSection/@ownedClassifier.1/@ownedPortConnection.1"      }    }, {      "context" :"/",      "source" :"//@componentInstance.1/@featureInstance.1",      "destination" :"//@featureInstance.4",      "connection" :{        "type" :"aadl2:PortConnection",        "href" :"../../github/AADLib/examples/fms/subsystem.aadl#/0/@ownedPublicSection/@ownedClassifier.6/@ownedPortConnection.3"      }    } ]  }, {    "name" :"fm1.FM1.th_wpInfo1 -> ph_wpInfo1",    "kind" :"portConnection",    "destination" :"//@featureInstance.5",    "source" :"//@componentInstance.1/@componentInstance.0/@featureInstance.3",    "connectionReference" :[ {      "context" :"//@componentInstance.1",      "source" :"//@componentInstance.1/@componentInstance.0/@featureInstance.3",      "destination" :"//@componentInstance.1/@featureInstance.3",      "connection" :{        "type" :"aadl2:PortConnection",        "href" :"../../github/AADLib/examples/fms/m2_software.aadl#/0/@ownedPublicSection/@ownedClassifier.1/@ownedPortConnection.3"      }    }, {      "context" :"/",      "source" :"//@componentInstance.1/@featureInstance.3",      "destination" :"//@featureInstance.5",      "connection" :{        "type" :"aadl2:PortConnection",        "href" :"../../github/AADLib/examples/fms/subsystem.aadl#/0/@ownedPublicSection/@ownedClassifier.6/@ownedPortConnection.4"      }    } ]  }, {    "name" :"fm1.FM1.th_ETA1 -> ph_ETA1",    "kind" :"portConnection",    "destination" :"//@featureInstance.6",    "source" :"//@componentInstance.1/@componentInstance.0/@featureInstance.5",    "connectionReference" :[ {      "context" :"//@componentInstance.1",      "source" :"//@componentInstance.1/@componentInstance.0/@featureInstance.5",      "destination" :"//@componentInstance.1/@featureInstance.5",      "connection" :{        "type" :"aadl2:PortConnection",        "href" :"../../github/AADLib/examples/fms/m2_software.aadl#/0/@ownedPublicSection/@ownedClassifier.1/@ownedPortConnection.5"      }    }, {      "context" :"/",      "source" :"//@componentInstance.1/@featureInstance.5",      "destination" :"//@featureInstance.6",      "connection" :{        "type" :"aadl2:PortConnection",        "href" :"../../github/AADLib/examples/fms/subsystem.aadl#/0/@ownedPublicSection/@ownedClassifier.6/@ownedPortConnection.5"      }    } ]  } ],  "classifier" :{    "type" :"aadl2:SystemImplementation",    "href" :"../../github/AADLib/examples/fms/subsystem.aadl#subsystem.m2_system.impl"  },  "systemOperationMode" :{    "name" :"No Modes"  },  "componentImplementation" :{    "type" :"aadl2:SystemImplementation",    "href" :"../../github/AADLib/examples/fms/subsystem.aadl#subsystem.m2_system.impl"  }}