{  "version" :"2.0",  "name" :"IS3MS_impl_Instance",  "category" :"system",  "featureInstance" :[ {    "name" :"et1",    "direction" :"in out",    "feature" :{      "type" :"aadl2:DataPort",      "href" :"../../github/APS-Communication_Architecture/APS.aadl#/0/@ownedPublicSection/@ownedClassifier.61/@ownedDataPort.0"    }  }, {    "name" :"et2",    "direction" :"in out",    "feature" :{      "type" :"aadl2:DataPort",      "href" :"../../github/APS-Communication_Architecture/APS.aadl#/0/@ownedPublicSection/@ownedClassifier.61/@ownedDataPort.1"    }  } ],  "componentInstance" :[ {    "name" :"NICTeaming",    "category" :"process",    "featureInstance" :[ {      "name" :"Veth1",      "direction" :"in out",      "feature" :{        "type" :"aadl2:DataPort",        "href" :"../../github/APS-Communication_Architecture/APS.aadl#/0/@ownedPublicSection/@ownedClassifier.67/@ownedDataPort.0"      }    }, {      "name" :"Veth2",      "direction" :"in out",      "feature" :{        "type" :"aadl2:DataPort",        "href" :"../../github/APS-Communication_Architecture/APS.aadl#/0/@ownedPublicSection/@ownedClassifier.67/@ownedDataPort.1"      }    }, {      "name" :"Teamedeth",      "direction" :"in out",      "feature" :{        "type" :"aadl2:DataPort",        "href" :"../../github/APS-Communication_Architecture/APS.aadl#/0/@ownedPublicSection/@ownedClassifier.67/@ownedDataPort.2"      }    } ],    "subcomponent" :{      "type" :"aadl2:ProcessSubcomponent",      "href" :"../../github/APS-Communication_Architecture/APS.aadl#/0/@ownedPublicSection/@ownedClassifier.62/@ownedProcessSubcomponent.0"    },    "index" :"0",    "classifier" :{      "type" :"aadl2:ProcessType",      "href" :"../../github/APS-Communication_Architecture/APS.aadl#APS.NICTeaming"    }  }, {    "name" :"SIEM",    "category" :"process",    "featureInstance" :{      "name" :"DataPort",      "direction" :"in out",      "feature" :{        "type" :"aadl2:DataPort",        "href" :"../../github/APS-Communication_Architecture/APS.aadl#/0/@ownedPublicSection/@ownedClassifier.63/@ownedDataPort.0"      }    },    "subcomponent" :{      "type" :"aadl2:ProcessSubcomponent",      "href" :"../../github/APS-Communication_Architecture/APS.aadl#/0/@ownedPublicSection/@ownedClassifier.62/@ownedProcessSubcomponent.1"    },    "index" :"0",    "classifier" :{      "type" :"aadl2:ProcessType",      "href" :"../../github/APS-Communication_Architecture/APS.aadl#APS.SIEM"    }  } ],  "connectionInstance" :[ {    "name" :"et1 -> NICTeaming.Veth1",    "kind" :"portConnection",    "destination" :"//@componentInstance.0/@featureInstance.0",    "source" :"//@featureInstance.0",    "connectionReference" :{      "context" :"/",      "source" :"//@featureInstance.0",      "destination" :"//@componentInstance.0/@featureInstance.0",      "reverse" :"true",      "connection" :{        "type" :"aadl2:PortConnection",        "href" :"../../github/APS-Communication_Architecture/APS.aadl#/0/@ownedPublicSection/@ownedClassifier.62/@ownedPortConnection.0"      }    }  }, {    "name" :"et2 -> NICTeaming.Veth2",    "kind" :"portConnection",    "destination" :"//@componentInstance.0/@featureInstance.1",    "source" :"//@featureInstance.1",    "connectionReference" :{      "context" :"/",      "source" :"//@featureInstance.1",      "destination" :"//@componentInstance.0/@featureInstance.1",      "reverse" :"true",      "connection" :{        "type" :"aadl2:PortConnection",        "href" :"../../github/APS-Communication_Architecture/APS.aadl#/0/@ownedPublicSection/@ownedClassifier.62/@ownedPortConnection.1"      }    }  }, {    "name" :"NICTeaming.Veth1 -> et1",    "kind" :"portConnection",    "destination" :"//@featureInstance.0",    "source" :"//@componentInstance.0/@featureInstance.0",    "connectionReference" :{      "context" :"/",      "source" :"//@componentInstance.0/@featureInstance.0",      "destination" :"//@featureInstance.0",      "connection" :{        "type" :"aadl2:PortConnection",        "href" :"../../github/APS-Communication_Architecture/APS.aadl#/0/@ownedPublicSection/@ownedClassifier.62/@ownedPortConnection.0"      }    }  }, {    "name" :"NICTeaming.Veth2 -> et2",    "kind" :"portConnection",    "destination" :"//@featureInstance.1",    "source" :"//@componentInstance.0/@featureInstance.1",    "connectionReference" :{      "context" :"/",      "source" :"//@componentInstance.0/@featureInstance.1",      "destination" :"//@featureInstance.1",      "connection" :{        "type" :"aadl2:PortConnection",        "href" :"../../github/APS-Communication_Architecture/APS.aadl#/0/@ownedPublicSection/@ownedClassifier.62/@ownedPortConnection.1"      }    }  }, {    "name" :"NICTeaming.Teamedeth -> SIEM.DataPort",    "complete" :"true",    "kind" :"portConnection",    "destination" :"//@componentInstance.1/@featureInstance.0",    "source" :"//@componentInstance.0/@featureInstance.2",    "connectionReference" :{      "context" :"/",      "source" :"//@componentInstance.0/@featureInstance.2",      "destination" :"//@componentInstance.1/@featureInstance.0",      "connection" :{        "type" :"aadl2:PortConnection",        "href" :"../../github/APS-Communication_Architecture/APS.aadl#/0/@ownedPublicSection/@ownedClassifier.62/@ownedPortConnection.2"      }    }  }, {    "name" :"SIEM.DataPort -> NICTeaming.Teamedeth",    "complete" :"true",    "kind" :"portConnection",    "destination" :"//@componentInstance.0/@featureInstance.2",    "source" :"//@componentInstance.1/@featureInstance.0",    "connectionReference" :{      "context" :"/",      "source" :"//@componentInstance.1/@featureInstance.0",      "destination" :"//@componentInstance.0/@featureInstance.2",      "reverse" :"true",      "connection" :{        "type" :"aadl2:PortConnection",        "href" :"../../github/APS-Communication_Architecture/APS.aadl#/0/@ownedPublicSection/@ownedClassifier.62/@ownedPortConnection.2"      }    }  } ],  "classifier" :{    "type" :"aadl2:SystemImplementation",    "href" :"../../github/APS-Communication_Architecture/APS.aadl#APS.IS3MS.impl"  },  "systemOperationMode" :{    "name" :"No Modes"  },  "componentImplementation" :{    "type" :"aadl2:SystemImplementation",    "href" :"../../github/APS-Communication_Architecture/APS.aadl#APS.IS3MS.impl"  }}