{  "version" :"2.0",  "name" :"S_I_Instance",  "category" :"system",  "componentInstance" :{    "name" :"Proc",    "category" :"process",    "componentInstance" :[ {      "name" :"TT1",      "category" :"thread",      "ownedPropertyAssociation" :[ {        "type" :"instance:PropertyAssociationInstance",        "property" :{          "href" :"../../github/ocarina/resources/AADLv2/programming_properties.aadl#Programming_Properties.Compute_Entrypoint"        },        "ownedValue" :{          "ownedValue" :{            "type" :"aadl2:StringLiteral",            "value" :"a"          }        },        "propertyAssociation" :{          "href" :"../../github/ocarina/tests/SAE-test-examples-09152005/TestComputeEntryPoint.aadl#/0/@ownedPublicSection/@ownedClassifier.1/@ownedPropertyAssociation.0"        }      }, {        "type" :"instance:PropertyAssociationInstance",        "property" :{          "href" :"../../github/ocarina/resources/AADLv2/timing_properties.aadl#Timing_Properties.Period"        },        "ownedValue" :{          "ownedValue" :{            "type" :"aadl2:IntegerLiteral",            "value" :"1",            "unit" :{              "href" :"../../github/ocarina/resources/AADLv1/aadl_project.aadl#/0/@ownedPropertyType.9/@ownedLiteral.3"            }          }        },        "propertyAssociation" :{          "href" :"../../github/ocarina/tests/SAE-test-examples-09152005/TestComputeEntryPoint.aadl#/0/@ownedPublicSection/@ownedClassifier.0/@ownedPropertyAssociation.0"        }      } ],      "subcomponent" :{        "type" :"aadl2:ThreadSubcomponent",        "href" :"../../github/ocarina/tests/SAE-test-examples-09152005/TestComputeEntryPoint.aadl#/0/@ownedPublicSection/@ownedClassifier.4/@ownedThreadSubcomponent.0"      },      "index" :"0",      "classifier" :{        "type" :"aadl2:ThreadImplementation",        "href" :"../../github/ocarina/tests/SAE-test-examples-09152005/TestComputeEntryPoint.aadl#TestComputeEntryPoint.T.I"      }    }, {      "name" :"TT2",      "category" :"thread",      "ownedPropertyAssociation" :[ {        "type" :"instance:PropertyAssociationInstance",        "property" :{          "href" :"../../github/ocarina/resources/AADLv2/programming_properties.aadl#Programming_Properties.Compute_Entrypoint"        },        "ownedValue" :{          "inMode" :"//@systemOperationMode.0",          "ownedValue" :{            "type" :"aadl2:StringLiteral",            "value" :"b"          }        },        "propertyAssociation" :{          "href" :"../../github/ocarina/tests/SAE-test-examples-09152005/TestComputeEntryPoint.aadl#/0/@ownedPublicSection/@ownedClassifier.2/@ownedPropertyAssociation.0"        }      }, {        "type" :"instance:PropertyAssociationInstance",        "property" :{          "href" :"../../github/ocarina/resources/AADLv2/timing_properties.aadl#Timing_Properties.Period"        },        "ownedValue" :{          "ownedValue" :{            "type" :"aadl2:IntegerLiteral",            "value" :"1",            "unit" :{              "href" :"../../github/ocarina/resources/AADLv1/aadl_project.aadl#/0/@ownedPropertyType.9/@ownedLiteral.3"            }          }        },        "propertyAssociation" :{          "href" :"../../github/ocarina/tests/SAE-test-examples-09152005/TestComputeEntryPoint.aadl#/0/@ownedPublicSection/@ownedClassifier.0/@ownedPropertyAssociation.0"        }      } ],      "modeInstance" :[ {        "name" :"A",        "initial" :"true",        "mode" :{          "href" :"../../github/ocarina/tests/SAE-test-examples-09152005/TestComputeEntryPoint.aadl#/0/@ownedPublicSection/@ownedClassifier.2/@ownedMode.0"        }      }, {        "name" :"B",        "mode" :{          "href" :"../../github/ocarina/tests/SAE-test-examples-09152005/TestComputeEntryPoint.aadl#/0/@ownedPublicSection/@ownedClassifier.2/@ownedMode.1"        }      } ],      "subcomponent" :{        "type" :"aadl2:ThreadSubcomponent",        "href" :"../../github/ocarina/tests/SAE-test-examples-09152005/TestComputeEntryPoint.aadl#/0/@ownedPublicSection/@ownedClassifier.4/@ownedThreadSubcomponent.1"      },      "index" :"0",      "classifier" :{        "type" :"aadl2:ThreadImplementation",        "href" :"../../github/ocarina/tests/SAE-test-examples-09152005/TestComputeEntryPoint.aadl#TestComputeEntryPoint.T.I2"      }    } ],    "subcomponent" :{      "type" :"aadl2:ProcessSubcomponent",      "href" :"../../github/ocarina/tests/SAE-test-examples-09152005/TestComputeEntryPoint.aadl#/0/@ownedPublicSection/@ownedClassifier.6/@ownedProcessSubcomponent.0"    },    "index" :"0",    "classifier" :{      "type" :"aadl2:ProcessImplementation",      "href" :"../../github/ocarina/tests/SAE-test-examples-09152005/TestComputeEntryPoint.aadl#TestComputeEntryPoint.P.I"    }  },  "classifier" :{    "type" :"aadl2:SystemImplementation",    "href" :"../../github/ocarina/tests/SAE-test-examples-09152005/TestComputeEntryPoint.aadl#TestComputeEntryPoint.S.I"  },  "systemOperationMode" :[ {    "name" :"som_1",    "currentMode" :"//@componentInstance.0/@componentInstance.1/@modeInstance.0"  }, {    "name" :"som_2",    "currentMode" :"//@componentInstance.0/@componentInstance.1/@modeInstance.1"  } ],  "componentImplementation" :{    "type" :"aadl2:SystemImplementation",    "href" :"../../github/ocarina/tests/SAE-test-examples-09152005/TestComputeEntryPoint.aadl#TestComputeEntryPoint.S.I"  }}