{  "version" :"2.0",  "name" :"Retract_EV_System_impl_Instance",  "category" :"system",  "featureInstance" :[ {    "name" :"Retract_EV_System_Hout",    "category" :"busAccess",    "feature" :{      "type" :"aadl2:BusAccess",      "href" :"../../github/tpAADL/lgs.aadl#/0/@ownedPublicSection/@ownedClassifier.28/@ownedBusAccess.0"    },    "type" :{      "href" :"../../github/tpAADL/instances/lgs_Retract_EV_System_impl_Instance.aaxl2#/0"    }  }, {    "name" :"Retract_EV_System_Hin",    "category" :"busAccess",    "feature" :{      "type" :"aadl2:BusAccess",      "href" :"../../github/tpAADL/lgs.aadl#/0/@ownedPublicSection/@ownedClassifier.28/@ownedBusAccess.1"    },    "type" :{      "href" :"../../github/tpAADL/instances/lgs_Retract_EV_System_impl_Instance.aaxl2#/1"    }  }, {    "name" :"RetractEv",    "feature" :{      "type" :"aadl2:DataPort",      "href" :"../../github/tpAADL/lgs.aadl#/0/@ownedPublicSection/@ownedClassifier.28/@ownedDataPort.0"    },    "type" :{      "href" :"../../github/tpAADL/instances/lgs_Retract_EV_System_impl_Instance.aaxl2#/2"    }  } ],  "classifier" :{    "type" :"aadl2:SystemImplementation",    "href" :"../../github/tpAADL/lgs.aadl#lgs.Retract_EV_System.impl"  },  "systemOperationMode" :{    "name" :"No Modes"  },  "componentImplementation" :{    "type" :"aadl2:SystemImplementation",    "href" :"../../github/tpAADL/lgs.aadl#lgs.Retract_EV_System.impl"  }}