{  "version" :"2.0",  "name" :"lgsSystem_impl_Instance",  "category" :"system",  "componentInstance" :[ {    "name" :"GeneralHydrolicFlowBus",    "category" :"bus",    "subcomponent" :{      "type" :"aadl2:BusSubcomponent",      "href" :"../../github/tpAADL/lgs.aadl#/0/@ownedPublicSection/@ownedClassifier.25/@ownedBusSubcomponent.0"    },    "index" :"0",    "classifier" :{      "type" :"aadl2:AbstractType",      "href" :"../../github/tpAADL/lgs.aadl#|::0.5.9.25.45.0::18::/5"    }  }, {    "name" :"DigitalPart",    "category" :"system",    "featureInstance" :[ {      "name" :"CloseEv",      "direction" :"out",      "feature" :{        "type" :"aadl2:DataPort",        "href" :"../../github/tpAADL/lgs.aadl#/0/@ownedPublicSection/@ownedClassifier.0/@ownedDataPort.0"      },      "type" :{        "href" :"../../github/tpAADL/instances/lgs_lgsSystem_impl_Instance.aaxl2#/0"      }    }, {      "name" :"OpenEv",      "direction" :"out",      "feature" :{        "type" :"aadl2:DataPort",        "href" :"../../github/tpAADL/lgs.aadl#/0/@ownedPublicSection/@ownedClassifier.0/@ownedDataPort.1"      },      "type" :{        "href" :"../../github/tpAADL/instances/lgs_lgsSystem_impl_Instance.aaxl2#/1"      }    }, {      "name" :"RetractEv",      "direction" :"out",      "feature" :{        "type" :"aadl2:DataPort",        "href" :"../../github/tpAADL/lgs.aadl#/0/@ownedPublicSection/@ownedClassifier.0/@ownedDataPort.2"      },      "type" :{        "href" :"../../github/tpAADL/instances/lgs_lgsSystem_impl_Instance.aaxl2#/2"      }    }, {      "name" :"ExtendEv",      "direction" :"out",      "feature" :{        "type" :"aadl2:DataPort",        "href" :"../../github/tpAADL/lgs.aadl#/0/@ownedPublicSection/@ownedClassifier.0/@ownedDataPort.3"      },      "type" :{        "href" :"../../github/tpAADL/instances/lgs_lgsSystem_impl_Instance.aaxl2#/3"      }    }, {      "name" :"h",      "category" :"eventPort",      "feature" :{        "type" :"aadl2:EventPort",        "href" :"../../github/tpAADL/lgs.aadl#/0/@ownedPublicSection/@ownedClassifier.0/@ownedEventPort.0"      }    }, {      "name" :"gv",      "category" :"eventPort",      "direction" :"out",      "feature" :{        "type" :"aadl2:EventPort",        "href" :"../../github/tpAADL/lgs.aadl#/0/@ownedPublicSection/@ownedClassifier.0/@ownedEventPort.1"      }    } ],    "subcomponent" :{      "type" :"aadl2:SystemSubcomponent",      "href" :"../../github/tpAADL/lgs.aadl#/0/@ownedPublicSection/@ownedClassifier.25/@ownedSystemSubcomponent.0"    },    "index" :"0",    "classifier" :{      "type" :"aadl2:SystemImplementation",      "href" :"../../github/tpAADL/lgs.aadl#lgs.digital_part.impl"    }  }, {    "name" :"ElectrovalvesSystem",    "category" :"system",    "featureInstance" :[ {      "name" :"GenralHydrolicFloww",      "category" :"busAccess",      "feature" :{        "type" :"aadl2:BusAccess",        "href" :"../../github/tpAADL/lgs.aadl#/0/@ownedPublicSection/@ownedClassifier.48/@ownedBusAccess.0"      },      "type" :{        "href" :"../../github/tpAADL/instances/lgs_lgsSystem_impl_Instance.aaxl2#/28"      }    }, {      "name" :"CloeEV",      "feature" :{        "type" :"aadl2:DataPort",        "href" :"../../github/tpAADL/lgs.aadl#/0/@ownedPublicSection/@ownedClassifier.48/@ownedDataPort.0"      },      "type" :{        "href" :"../../github/tpAADL/instances/lgs_lgsSystem_impl_Instance.aaxl2#/29"      }    }, {      "name" :"OpenEv",      "feature" :{        "type" :"aadl2:DataPort",        "href" :"../../github/tpAADL/lgs.aadl#/0/@ownedPublicSection/@ownedClassifier.48/@ownedDataPort.1"      },      "type" :{        "href" :"../../github/tpAADL/instances/lgs_lgsSystem_impl_Instance.aaxl2#/30"      }    }, {      "name" :"ExtendEv",      "feature" :{        "type" :"aadl2:DataPort",        "href" :"../../github/tpAADL/lgs.aadl#/0/@ownedPublicSection/@ownedClassifier.48/@ownedDataPort.2"      },      "type" :{        "href" :"../../github/tpAADL/instances/lgs_lgsSystem_impl_Instance.aaxl2#/31"      }    }, {      "name" :"RetractEv",      "feature" :{        "type" :"aadl2:DataPort",        "href" :"../../github/tpAADL/lgs.aadl#/0/@ownedPublicSection/@ownedClassifier.48/@ownedDataPort.3"      },      "type" :{        "href" :"../../github/tpAADL/instances/lgs_lgsSystem_impl_Instance.aaxl2#/32"      }    } ],    "componentInstance" :[ {      "name" :"ExtensionCircuit_OpenDoorEV_HydrolicBus",      "category" :"bus",      "subcomponent" :{        "type" :"aadl2:BusSubcomponent",        "href" :"../../github/tpAADL/lgs.aadl#/0/@ownedPublicSection/@ownedClassifier.49/@ownedBusSubcomponent.0"      },      "index" :"0",      "classifier" :{        "type" :"aadl2:AbstractType",        "href" :"../../github/tpAADL/lgs.aadl#|::0.5.9.49.45.0::18::/5"      }    }, {      "name" :"RetractationCircuit_RetractEv_HydrolicBus",      "category" :"bus",      "subcomponent" :{        "type" :"aadl2:BusSubcomponent",        "href" :"../../github/tpAADL/lgs.aadl#/0/@ownedPublicSection/@ownedClassifier.49/@ownedBusSubcomponent.1"      },      "index" :"0",      "classifier" :{        "type" :"aadl2:AbstractType",        "href" :"../../github/tpAADL/lgs.aadl#|::0.5.9.49.45.1::18::/5"      }    }, {      "name" :"RetractationCircuitHydrolicBus",      "category" :"bus",      "subcomponent" :{        "type" :"aadl2:BusSubcomponent",        "href" :"../../github/tpAADL/lgs.aadl#/0/@ownedPublicSection/@ownedClassifier.49/@ownedBusSubcomponent.2"      },      "index" :"0",      "classifier" :{        "type" :"aadl2:AbstractType",        "href" :"../../github/tpAADL/lgs.aadl#|::0.5.9.49.45.2::18::/5"      }    }, {      "name" :"RetractationCircuit_ExtendEv_HydrolicBus",      "category" :"bus",      "subcomponent" :{        "type" :"aadl2:BusSubcomponent",        "href" :"../../github/tpAADL/lgs.aadl#/0/@ownedPublicSection/@ownedClassifier.49/@ownedBusSubcomponent.3"      },      "index" :"0",      "classifier" :{        "type" :"aadl2:AbstractType",        "href" :"../../github/tpAADL/lgs.aadl#|::0.5.9.49.45.3::18::/5"      }    }, {      "name" :"FrontGearCylinder",      "category" :"device",      "featureInstance" :[ {        "name" :"FrontGearCylinderRetractationCircuit",        "category" :"busAccess",        "feature" :{          "type" :"aadl2:BusAccess",          "href" :"../../github/tpAADL/lgs.aadl#/0/@ownedPublicSection/@ownedClassifier.42/@ownedBusAccess.0"        },        "type" :{          "href" :"../../github/tpAADL/instances/lgs_lgsSystem_impl_Instance.aaxl2#/4"        }      }, {        "name" :"FrontGearCylinderExtensionCircuit",        "category" :"busAccess",        "feature" :{          "type" :"aadl2:BusAccess",          "href" :"../../github/tpAADL/lgs.aadl#/0/@ownedPublicSection/@ownedClassifier.42/@ownedBusAccess.1"        },        "type" :{          "href" :"../../github/tpAADL/instances/lgs_lgsSystem_impl_Instance.aaxl2#/5"        }      } ],      "subcomponent" :{        "type" :"aadl2:DeviceSubcomponent",        "href" :"../../github/tpAADL/lgs.aadl#/0/@ownedPublicSection/@ownedClassifier.49/@ownedDeviceSubcomponent.0"      },      "index" :"0",      "classifier" :{        "type" :"aadl2:DeviceImplementation",        "href" :"../../github/tpAADL/lgs.aadl#lgs.FrontGearCylinder.impl"      }    }, {      "name" :"RightGearCylinder",      "category" :"device",      "featureInstance" :[ {        "name" :"LeftGearCylinderRetractationCircuit",        "category" :"busAccess",        "feature" :{          "type" :"aadl2:BusAccess",          "href" :"../../github/tpAADL/lgs.aadl#/0/@ownedPublicSection/@ownedClassifier.46/@ownedBusAccess.0"        },        "type" :{          "href" :"../../github/tpAADL/instances/lgs_lgsSystem_impl_Instance.aaxl2#/6"        }      }, {        "name" :"LeftGearCylinderExtensionCircuit",        "category" :"busAccess",        "feature" :{          "type" :"aadl2:BusAccess",          "href" :"../../github/tpAADL/lgs.aadl#/0/@ownedPublicSection/@ownedClassifier.46/@ownedBusAccess.1"        },        "type" :{          "href" :"../../github/tpAADL/instances/lgs_lgsSystem_impl_Instance.aaxl2#/7"        }      } ],      "subcomponent" :{        "type" :"aadl2:DeviceSubcomponent",        "href" :"../../github/tpAADL/lgs.aadl#/0/@ownedPublicSection/@ownedClassifier.49/@ownedDeviceSubcomponent.1"      },      "index" :"0",      "classifier" :{        "type" :"aadl2:DeviceImplementation",        "href" :"../../github/tpAADL/lgs.aadl#lgs.LeftGearCylinder.impl"      }    }, {      "name" :"LeftDoorCylinder",      "category" :"device",      "featureInstance" :[ {        "name" :"LeftDoorCylinderRetractationCircuit",        "category" :"busAccess",        "feature" :{          "type" :"aadl2:BusAccess",          "href" :"../../github/tpAADL/lgs.aadl#/0/@ownedPublicSection/@ownedClassifier.40/@ownedBusAccess.0"        },        "type" :{          "href" :"../../github/tpAADL/instances/lgs_lgsSystem_impl_Instance.aaxl2#/8"        }      }, {        "name" :"LeftDoorCylinderExtensionCircuit",        "category" :"busAccess",        "feature" :{          "type" :"aadl2:BusAccess",          "href" :"../../github/tpAADL/lgs.aadl#/0/@ownedPublicSection/@ownedClassifier.40/@ownedBusAccess.1"        },        "type" :{          "href" :"../../github/tpAADL/instances/lgs_lgsSystem_impl_Instance.aaxl2#/9"        }      } ],      "subcomponent" :{        "type" :"aadl2:DeviceSubcomponent",        "href" :"../../github/tpAADL/lgs.aadl#/0/@ownedPublicSection/@ownedClassifier.49/@ownedDeviceSubcomponent.2"      },      "index" :"0",      "classifier" :{        "type" :"aadl2:DeviceImplementation",        "href" :"../../github/tpAADL/lgs.aadl#lgs.LeftDoorCylinder.impl"      }    }, {      "name" :"LeftGearCylinder",      "category" :"device",      "featureInstance" :[ {        "name" :"RightGearCylinderRetractationCircuit",        "category" :"busAccess",        "feature" :{          "type" :"aadl2:BusAccess",          "href" :"../../github/tpAADL/lgs.aadl#/0/@ownedPublicSection/@ownedClassifier.44/@ownedBusAccess.0"        },        "type" :{          "href" :"../../github/tpAADL/instances/lgs_lgsSystem_impl_Instance.aaxl2#/10"        }      }, {        "name" :"RightGearCylinderExtensionCircuit",        "category" :"busAccess",        "feature" :{          "type" :"aadl2:BusAccess",          "href" :"../../github/tpAADL/lgs.aadl#/0/@ownedPublicSection/@ownedClassifier.44/@ownedBusAccess.1"        },        "type" :{          "href" :"../../github/tpAADL/instances/lgs_lgsSystem_impl_Instance.aaxl2#/11"        }      } ],      "subcomponent" :{        "type" :"aadl2:DeviceSubcomponent",        "href" :"../../github/tpAADL/lgs.aadl#/0/@ownedPublicSection/@ownedClassifier.49/@ownedDeviceSubcomponent.3"      },      "index" :"0",      "classifier" :{        "type" :"aadl2:DeviceImplementation",        "href" :"../../github/tpAADL/lgs.aadl#lgs.RightGearCylinder.impl"      }    }, {      "name" :"RightDoorCylinder",      "category" :"device",      "featureInstance" :[ {        "name" :"RightDoorCylinderRetractationCircuit",        "category" :"busAccess",        "feature" :{          "type" :"aadl2:BusAccess",          "href" :"../../github/tpAADL/lgs.aadl#/0/@ownedPublicSection/@ownedClassifier.38/@ownedBusAccess.0"        },        "type" :{          "href" :"../../github/tpAADL/instances/lgs_lgsSystem_impl_Instance.aaxl2#/12"        }      }, {        "name" :"RightDoorCylinderExtensionCircuit",        "category" :"busAccess",        "feature" :{          "type" :"aadl2:BusAccess",          "href" :"../../github/tpAADL/lgs.aadl#/0/@ownedPublicSection/@ownedClassifier.38/@ownedBusAccess.1"        },        "type" :{          "href" :"../../github/tpAADL/instances/lgs_lgsSystem_impl_Instance.aaxl2#/13"        }      } ],      "subcomponent" :{        "type" :"aadl2:DeviceSubcomponent",        "href" :"../../github/tpAADL/lgs.aadl#/0/@ownedPublicSection/@ownedClassifier.49/@ownedDeviceSubcomponent.4"      },      "index" :"0",      "classifier" :{        "type" :"aadl2:DeviceImplementation",        "href" :"../../github/tpAADL/lgs.aadl#lgs.RightDoorCylinder.impl"      }    }, {      "name" :"FrontDoorCylinder",      "category" :"device",      "featureInstance" :[ {        "name" :"FrontDoorCylinderReatractionCircuit",        "category" :"busAccess",        "feature" :{          "type" :"aadl2:BusAccess",          "href" :"../../github/tpAADL/lgs.aadl#/0/@ownedPublicSection/@ownedClassifier.36/@ownedBusAccess.0"        },        "type" :{          "href" :"../../github/tpAADL/instances/lgs_lgsSystem_impl_Instance.aaxl2#/14"        }      }, {        "name" :"FrontDoorCylinder_ExtensionCircuit",        "category" :"busAccess",        "feature" :{          "type" :"aadl2:BusAccess",          "href" :"../../github/tpAADL/lgs.aadl#/0/@ownedPublicSection/@ownedClassifier.36/@ownedBusAccess.1"        },        "type" :{          "href" :"../../github/tpAADL/instances/lgs_lgsSystem_impl_Instance.aaxl2#/15"        }      } ],      "subcomponent" :{        "type" :"aadl2:DeviceSubcomponent",        "href" :"../../github/tpAADL/lgs.aadl#/0/@ownedPublicSection/@ownedClassifier.49/@ownedDeviceSubcomponent.5"      },      "index" :"0",      "classifier" :{        "type" :"aadl2:DeviceImplementation",        "href" :"../../github/tpAADL/lgs.aadl#lgs.FrontDoorCylinder.impl"      }    }, {      "name" :"lgsSystem_OpenDoorEvSystemImpl",      "category" :"system",      "featureInstance" :[ {        "name" :"Open_EV_System_Hout",        "category" :"busAccess",        "feature" :{          "type" :"aadl2:BusAccess",          "href" :"../../github/tpAADL/lgs.aadl#/0/@ownedPublicSection/@ownedClassifier.27/@ownedBusAccess.0"        },        "type" :{          "href" :"../../github/tpAADL/instances/lgs_lgsSystem_impl_Instance.aaxl2#/16"        }      }, {        "name" :"Open_EV_System_Hin",        "category" :"busAccess",        "feature" :{          "type" :"aadl2:BusAccess",          "href" :"../../github/tpAADL/lgs.aadl#/0/@ownedPublicSection/@ownedClassifier.27/@ownedBusAccess.1"        },        "type" :{          "href" :"../../github/tpAADL/instances/lgs_lgsSystem_impl_Instance.aaxl2#/17"        }      }, {        "name" :"OpenEv",        "feature" :{          "type" :"aadl2:DataPort",          "href" :"../../github/tpAADL/lgs.aadl#/0/@ownedPublicSection/@ownedClassifier.27/@ownedDataPort.0"        },        "type" :{          "href" :"../../github/tpAADL/instances/lgs_lgsSystem_impl_Instance.aaxl2#/18"        }      } ],      "subcomponent" :{        "type" :"aadl2:SystemSubcomponent",        "href" :"../../github/tpAADL/lgs.aadl#/0/@ownedPublicSection/@ownedClassifier.49/@ownedSystemSubcomponent.0"      },      "index" :"0",      "classifier" :{        "type" :"aadl2:SystemImplementation",        "href" :"../../github/tpAADL/lgs.aadl#lgs.Open_EV_System.impl"      }    }, {      "name" :"lgsSystem_CloseDoorEvSystemImpl",      "category" :"system",      "featureInstance" :[ {        "name" :"CloseDoorsEvSystem_Hout",        "category" :"busAccess",        "feature" :{          "type" :"aadl2:BusAccess",          "href" :"../../github/tpAADL/lgs.aadl#/0/@ownedPublicSection/@ownedClassifier.26/@ownedBusAccess.0"        },        "type" :{          "href" :"../../github/tpAADL/instances/lgs_lgsSystem_impl_Instance.aaxl2#/19"        }      }, {        "name" :"CloseDoorsEvSystem_Hin",        "category" :"busAccess",        "feature" :{          "type" :"aadl2:BusAccess",          "href" :"../../github/tpAADL/lgs.aadl#/0/@ownedPublicSection/@ownedClassifier.26/@ownedBusAccess.1"        },        "type" :{          "href" :"../../github/tpAADL/instances/lgs_lgsSystem_impl_Instance.aaxl2#/20"        }      }, {        "name" :"CloeEV",        "feature" :{          "type" :"aadl2:DataPort",          "href" :"../../github/tpAADL/lgs.aadl#/0/@ownedPublicSection/@ownedClassifier.26/@ownedDataPort.0"        },        "type" :{          "href" :"../../github/tpAADL/instances/lgs_lgsSystem_impl_Instance.aaxl2#/21"        }      } ],      "subcomponent" :{        "type" :"aadl2:SystemSubcomponent",        "href" :"../../github/tpAADL/lgs.aadl#/0/@ownedPublicSection/@ownedClassifier.49/@ownedSystemSubcomponent.1"      },      "index" :"0",      "classifier" :{        "type" :"aadl2:SystemImplementation",        "href" :"../../github/tpAADL/lgs.aadl#lgs.Close_EV_System.impl"      }    }, {      "name" :"lgsSystem_ExtendEvSystemImpl",      "category" :"system",      "featureInstance" :[ {        "name" :"Extend_EV_System_Hout",        "category" :"busAccess",        "feature" :{          "type" :"aadl2:BusAccess",          "href" :"../../github/tpAADL/lgs.aadl#/0/@ownedPublicSection/@ownedClassifier.29/@ownedBusAccess.0"        },        "type" :{          "href" :"../../github/tpAADL/instances/lgs_lgsSystem_impl_Instance.aaxl2#/22"        }      }, {        "name" :"Extend_EV_System_Hin",        "category" :"busAccess",        "feature" :{          "type" :"aadl2:BusAccess",          "href" :"../../github/tpAADL/lgs.aadl#/0/@ownedPublicSection/@ownedClassifier.29/@ownedBusAccess.1"        },        "type" :{          "href" :"../../github/tpAADL/instances/lgs_lgsSystem_impl_Instance.aaxl2#/23"        }      }, {        "name" :"ExtendEv",        "feature" :{          "type" :"aadl2:DataPort",          "href" :"../../github/tpAADL/lgs.aadl#/0/@ownedPublicSection/@ownedClassifier.29/@ownedDataPort.0"        },        "type" :{          "href" :"../../github/tpAADL/instances/lgs_lgsSystem_impl_Instance.aaxl2#/24"        }      } ],      "subcomponent" :{        "type" :"aadl2:SystemSubcomponent",        "href" :"../../github/tpAADL/lgs.aadl#/0/@ownedPublicSection/@ownedClassifier.49/@ownedSystemSubcomponent.2"      },      "index" :"0",      "classifier" :{        "type" :"aadl2:SystemImplementation",        "href" :"../../github/tpAADL/lgs.aadl#lgs.Extend_EV_System.impl"      }    }, {      "name" :"lgsSystem_RetractEvSystemImpl",      "category" :"system",      "featureInstance" :[ {        "name" :"Retract_EV_System_Hout",        "category" :"busAccess",        "feature" :{          "type" :"aadl2:BusAccess",          "href" :"../../github/tpAADL/lgs.aadl#/0/@ownedPublicSection/@ownedClassifier.28/@ownedBusAccess.0"        },        "type" :{          "href" :"../../github/tpAADL/instances/lgs_lgsSystem_impl_Instance.aaxl2#/25"        }      }, {        "name" :"Retract_EV_System_Hin",        "category" :"busAccess",        "feature" :{          "type" :"aadl2:BusAccess",          "href" :"../../github/tpAADL/lgs.aadl#/0/@ownedPublicSection/@ownedClassifier.28/@ownedBusAccess.1"        },        "type" :{          "href" :"../../github/tpAADL/instances/lgs_lgsSystem_impl_Instance.aaxl2#/26"        }      }, {        "name" :"RetractEv",        "feature" :{          "type" :"aadl2:DataPort",          "href" :"../../github/tpAADL/lgs.aadl#/0/@ownedPublicSection/@ownedClassifier.28/@ownedDataPort.0"        },        "type" :{          "href" :"../../github/tpAADL/instances/lgs_lgsSystem_impl_Instance.aaxl2#/27"        }      } ],      "subcomponent" :{        "type" :"aadl2:SystemSubcomponent",        "href" :"../../github/tpAADL/lgs.aadl#/0/@ownedPublicSection/@ownedClassifier.49/@ownedSystemSubcomponent.3"      },      "index" :"0",      "classifier" :{        "type" :"aadl2:SystemImplementation",        "href" :"../../github/tpAADL/lgs.aadl#lgs.Retract_EV_System.impl"      }    } ],    "connectionInstance" :[ {      "name" :"FrontGearCylinder.FrontGearCylinderRetractationCircuit -> RetractationCircuit_ExtendEv_HydrolicBus",      "complete" :"true",      "kind" :"accessConnection",      "destination" :"//@componentInstance.2/@componentInstance.3",      "source" :"//@componentInstance.2/@componentInstance.4/@featureInstance.0",      "connectionReference" :{        "context" :"//@componentInstance.2",        "source" :"//@componentInstance.2/@componentInstance.4/@featureInstance.0",        "destination" :"//@componentInstance.2/@componentInstance.3",        "connection" :{          "type" :"aadl2:AccessConnection",          "href" :"../../github/tpAADL/lgs.aadl#/0/@ownedPublicSection/@ownedClassifier.49/@ownedAccessConnection.3"        }      }    }, {      "name" :"FrontGearCylinder.FrontGearCylinderExtensionCircuit -> RetractationCircuit_RetractEv_HydrolicBus",      "complete" :"true",      "kind" :"accessConnection",      "destination" :"//@componentInstance.2/@componentInstance.1",      "source" :"//@componentInstance.2/@componentInstance.4/@featureInstance.1",      "connectionReference" :{        "context" :"//@componentInstance.2",        "source" :"//@componentInstance.2/@componentInstance.4/@featureInstance.1",        "destination" :"//@componentInstance.2/@componentInstance.1",        "connection" :{          "type" :"aadl2:AccessConnection",          "href" :"../../github/tpAADL/lgs.aadl#/0/@ownedPublicSection/@ownedClassifier.49/@ownedAccessConnection.8"        }      }    }, {      "name" :"RightGearCylinder.LeftGearCylinderRetractationCircuit -> RetractationCircuit_ExtendEv_HydrolicBus",      "complete" :"true",      "kind" :"accessConnection",      "destination" :"//@componentInstance.2/@componentInstance.3",      "source" :"//@componentInstance.2/@componentInstance.5/@featureInstance.0",      "connectionReference" :{        "context" :"//@componentInstance.2",        "source" :"//@componentInstance.2/@componentInstance.5/@featureInstance.0",        "destination" :"//@componentInstance.2/@componentInstance.3",        "connection" :{          "type" :"aadl2:AccessConnection",          "href" :"../../github/tpAADL/lgs.aadl#/0/@ownedPublicSection/@ownedClassifier.49/@ownedAccessConnection.4"        }      }    }, {      "name" :"RightGearCylinder.LeftGearCylinderExtensionCircuit -> RetractationCircuit_RetractEv_HydrolicBus",      "complete" :"true",      "kind" :"accessConnection",      "destination" :"//@componentInstance.2/@componentInstance.1",      "source" :"//@componentInstance.2/@componentInstance.5/@featureInstance.1",      "connectionReference" :{        "context" :"//@componentInstance.2",        "source" :"//@componentInstance.2/@componentInstance.5/@featureInstance.1",        "destination" :"//@componentInstance.2/@componentInstance.1",        "connection" :{          "type" :"aadl2:AccessConnection",          "href" :"../../github/tpAADL/lgs.aadl#/0/@ownedPublicSection/@ownedClassifier.49/@ownedAccessConnection.7"        }      }    }, {      "name" :"LeftDoorCylinder.LeftDoorCylinderRetractationCircuit -> RetractationCircuitHydrolicBus",      "complete" :"true",      "kind" :"accessConnection",      "destination" :"//@componentInstance.2/@componentInstance.2",      "source" :"//@componentInstance.2/@componentInstance.6/@featureInstance.0",      "connectionReference" :{        "context" :"//@componentInstance.2",        "source" :"//@componentInstance.2/@componentInstance.6/@featureInstance.0",        "destination" :"//@componentInstance.2/@componentInstance.2",        "connection" :{          "type" :"aadl2:AccessConnection",          "href" :"../../github/tpAADL/lgs.aadl#/0/@ownedPublicSection/@ownedClassifier.49/@ownedAccessConnection.2"        }      }    }, {      "name" :"LeftDoorCylinder.LeftDoorCylinderExtensionCircuit -> ExtensionCircuit_OpenDoorEV_HydrolicBus",      "complete" :"true",      "kind" :"accessConnection",      "destination" :"//@componentInstance.2/@componentInstance.0",      "source" :"//@componentInstance.2/@componentInstance.6/@featureInstance.1",      "connectionReference" :{        "context" :"//@componentInstance.2",        "source" :"//@componentInstance.2/@componentInstance.6/@featureInstance.1",        "destination" :"//@componentInstance.2/@componentInstance.0",        "connection" :{          "type" :"aadl2:AccessConnection",          "href" :"../../github/tpAADL/lgs.aadl#/0/@ownedPublicSection/@ownedClassifier.49/@ownedAccessConnection.9"        }      }    }, {      "name" :"LeftGearCylinder.RightGearCylinderRetractationCircuit -> RetractationCircuit_ExtendEv_HydrolicBus",      "complete" :"true",      "kind" :"accessConnection",      "destination" :"//@componentInstance.2/@componentInstance.3",      "source" :"//@componentInstance.2/@componentInstance.7/@featureInstance.0",      "connectionReference" :{        "context" :"//@componentInstance.2",        "source" :"//@componentInstance.2/@componentInstance.7/@featureInstance.0",        "destination" :"//@componentInstance.2/@componentInstance.3",        "connection" :{          "type" :"aadl2:AccessConnection",          "href" :"../../github/tpAADL/lgs.aadl#/0/@ownedPublicSection/@ownedClassifier.49/@ownedAccessConnection.5"        }      }    }, {      "name" :"LeftGearCylinder.RightGearCylinderExtensionCircuit -> RetractationCircuit_RetractEv_HydrolicBus",      "complete" :"true",      "kind" :"accessConnection",      "destination" :"//@componentInstance.2/@componentInstance.1",      "source" :"//@componentInstance.2/@componentInstance.7/@featureInstance.1",      "connectionReference" :{        "context" :"//@componentInstance.2",        "source" :"//@componentInstance.2/@componentInstance.7/@featureInstance.1",        "destination" :"//@componentInstance.2/@componentInstance.1",        "connection" :{          "type" :"aadl2:AccessConnection",          "href" :"../../github/tpAADL/lgs.aadl#/0/@ownedPublicSection/@ownedClassifier.49/@ownedAccessConnection.6"        }      }    }, {      "name" :"RightDoorCylinder.RightDoorCylinderRetractationCircuit -> RetractationCircuitHydrolicBus",      "complete" :"true",      "kind" :"accessConnection",      "destination" :"//@componentInstance.2/@componentInstance.2",      "source" :"//@componentInstance.2/@componentInstance.8/@featureInstance.0",      "connectionReference" :{        "context" :"//@componentInstance.2",        "source" :"//@componentInstance.2/@componentInstance.8/@featureInstance.0",        "destination" :"//@componentInstance.2/@componentInstance.2",        "connection" :{          "type" :"aadl2:AccessConnection",          "href" :"../../github/tpAADL/lgs.aadl#/0/@ownedPublicSection/@ownedClassifier.49/@ownedAccessConnection.1"        }      }    }, {      "name" :"RightDoorCylinder.RightDoorCylinderExtensionCircuit -> RetractationCircuitHydrolicBus",      "complete" :"true",      "kind" :"accessConnection",      "destination" :"//@componentInstance.2/@componentInstance.2",      "source" :"//@componentInstance.2/@componentInstance.8/@featureInstance.1",      "connectionReference" :{        "context" :"//@componentInstance.2",        "source" :"//@componentInstance.2/@componentInstance.8/@featureInstance.1",        "destination" :"//@componentInstance.2/@componentInstance.2",        "connection" :{          "type" :"aadl2:AccessConnection",          "href" :"../../github/tpAADL/lgs.aadl#/0/@ownedPublicSection/@ownedClassifier.49/@ownedAccessConnection.10"        }      }    }, {      "name" :"FrontDoorCylinder.FrontDoorCylinderReatractionCircuit -> RetractationCircuitHydrolicBus",      "complete" :"true",      "kind" :"accessConnection",      "destination" :"//@componentInstance.2/@componentInstance.2",      "source" :"//@componentInstance.2/@componentInstance.9/@featureInstance.0",      "connectionReference" :{        "context" :"//@componentInstance.2",        "source" :"//@componentInstance.2/@componentInstance.9/@featureInstance.0",        "destination" :"//@componentInstance.2/@componentInstance.2",        "connection" :{          "type" :"aadl2:AccessConnection",          "href" :"../../github/tpAADL/lgs.aadl#/0/@ownedPublicSection/@ownedClassifier.49/@ownedAccessConnection.0"        }      }    }, {      "name" :"FrontDoorCylinder.FrontDoorCylinder_ExtensionCircuit -> RetractationCircuitHydrolicBus",      "complete" :"true",      "kind" :"accessConnection",      "destination" :"//@componentInstance.2/@componentInstance.2",      "source" :"//@componentInstance.2/@componentInstance.9/@featureInstance.1",      "connectionReference" :{        "context" :"//@componentInstance.2",        "source" :"//@componentInstance.2/@componentInstance.9/@featureInstance.1",        "destination" :"//@componentInstance.2/@componentInstance.2",        "connection" :{          "type" :"aadl2:AccessConnection",          "href" :"../../github/tpAADL/lgs.aadl#/0/@ownedPublicSection/@ownedClassifier.49/@ownedAccessConnection.11"        }      }    }, {      "name" :"lgsSystem_OpenDoorEvSystemImpl.Open_EV_System_Hout -> ExtensionCircuit_OpenDoorEV_HydrolicBus",      "complete" :"true",      "kind" :"accessConnection",      "destination" :"//@componentInstance.2/@componentInstance.0",      "source" :"//@componentInstance.2/@componentInstance.10/@featureInstance.0",      "connectionReference" :{        "context" :"//@componentInstance.2",        "source" :"//@componentInstance.2/@componentInstance.10/@featureInstance.0",        "destination" :"//@componentInstance.2/@componentInstance.0",        "connection" :{          "type" :"aadl2:AccessConnection",          "href" :"../../github/tpAADL/lgs.aadl#/0/@ownedPublicSection/@ownedClassifier.49/@ownedAccessConnection.13"        }      }    }, {      "name" :"lgsSystem_CloseDoorEvSystemImpl.CloseDoorsEvSystem_Hout -> RetractationCircuitHydrolicBus",      "complete" :"true",      "kind" :"accessConnection",      "destination" :"//@componentInstance.2/@componentInstance.2",      "source" :"//@componentInstance.2/@componentInstance.11/@featureInstance.0",      "connectionReference" :{        "context" :"//@componentInstance.2",        "source" :"//@componentInstance.2/@componentInstance.11/@featureInstance.0",        "destination" :"//@componentInstance.2/@componentInstance.2",        "connection" :{          "type" :"aadl2:AccessConnection",          "href" :"../../github/tpAADL/lgs.aadl#/0/@ownedPublicSection/@ownedClassifier.49/@ownedAccessConnection.12"        }      }    }, {      "name" :"lgsSystem_ExtendEvSystemImpl.Extend_EV_System_Hout -> RetractationCircuit_ExtendEv_HydrolicBus",      "complete" :"true",      "kind" :"accessConnection",      "destination" :"//@componentInstance.2/@componentInstance.3",      "source" :"//@componentInstance.2/@componentInstance.12/@featureInstance.0",      "connectionReference" :{        "context" :"//@componentInstance.2",        "source" :"//@componentInstance.2/@componentInstance.12/@featureInstance.0",        "destination" :"//@componentInstance.2/@componentInstance.3",        "connection" :{          "type" :"aadl2:AccessConnection",          "href" :"../../github/tpAADL/lgs.aadl#/0/@ownedPublicSection/@ownedClassifier.49/@ownedAccessConnection.14"        }      }    }, {      "name" :"lgsSystem_RetractEvSystemImpl.Retract_EV_System_Hout -> RetractationCircuit_RetractEv_HydrolicBus",      "complete" :"true",      "kind" :"accessConnection",      "destination" :"//@componentInstance.2/@componentInstance.1",      "source" :"//@componentInstance.2/@componentInstance.13/@featureInstance.0",      "connectionReference" :{        "context" :"//@componentInstance.2",        "source" :"//@componentInstance.2/@componentInstance.13/@featureInstance.0",        "destination" :"//@componentInstance.2/@componentInstance.1",        "connection" :{          "type" :"aadl2:AccessConnection",          "href" :"../../github/tpAADL/lgs.aadl#/0/@ownedPublicSection/@ownedClassifier.49/@ownedAccessConnection.15"        }      }    } ],    "subcomponent" :{      "type" :"aadl2:SystemSubcomponent",      "href" :"../../github/tpAADL/lgs.aadl#/0/@ownedPublicSection/@ownedClassifier.25/@ownedSystemSubcomponent.1"    },    "index" :"0",    "classifier" :{      "type" :"aadl2:SystemImplementation",      "href" :"../../github/tpAADL/lgs.aadl#lgs.ElectrovalvesSystem.impl"    }  } ],  "connectionInstance" :[ {    "name" :"DigitalPart.CloseEv -> ElectrovalvesSystem.lgsSystem_CloseDoorEvSystemImpl.CloeEV",    "complete" :"true",    "kind" :"portConnection",    "destination" :"//@componentInstance.2/@componentInstance.11/@featureInstance.2",    "source" :"//@componentInstance.1/@featureInstance.0",    "connectionReference" :[ {      "context" :"/",      "source" :"//@componentInstance.1/@featureInstance.0",      "destination" :"//@componentInstance.2/@featureInstance.1",      "connection" :{        "type" :"aadl2:FeatureConnection",        "href" :"../../github/tpAADL/lgs.aadl#/0/@ownedPublicSection/@ownedClassifier.25/@ownedFeatureConnection.2"      }    }, {      "context" :"//@componentInstance.2",      "source" :"//@componentInstance.2/@featureInstance.1",      "destination" :"//@componentInstance.2/@componentInstance.11/@featureInstance.2",      "connection" :{        "type" :"aadl2:FeatureConnection",        "href" :"../../github/tpAADL/lgs.aadl#/0/@ownedPublicSection/@ownedClassifier.49/@ownedFeatureConnection.2"      }    } ]  }, {    "name" :"DigitalPart.OpenEv -> ElectrovalvesSystem.lgsSystem_OpenDoorEvSystemImpl.OpenEv",    "complete" :"true",    "kind" :"portConnection",    "destination" :"//@componentInstance.2/@componentInstance.10/@featureInstance.2",    "source" :"//@componentInstance.1/@featureInstance.1",    "connectionReference" :[ {      "context" :"/",      "source" :"//@componentInstance.1/@featureInstance.1",      "destination" :"//@componentInstance.2/@featureInstance.2",      "connection" :{        "type" :"aadl2:FeatureConnection",        "href" :"../../github/tpAADL/lgs.aadl#/0/@ownedPublicSection/@ownedClassifier.25/@ownedFeatureConnection.3"      }    }, {      "context" :"//@componentInstance.2",      "source" :"//@componentInstance.2/@featureInstance.2",      "destination" :"//@componentInstance.2/@componentInstance.10/@featureInstance.2",      "connection" :{        "type" :"aadl2:FeatureConnection",        "href" :"../../github/tpAADL/lgs.aadl#/0/@ownedPublicSection/@ownedClassifier.49/@ownedFeatureConnection.0"      }    } ]  }, {    "name" :"DigitalPart.RetractEv -> ElectrovalvesSystem.lgsSystem_RetractEvSystemImpl.RetractEv",    "complete" :"true",    "kind" :"portConnection",    "destination" :"//@componentInstance.2/@componentInstance.13/@featureInstance.2",    "source" :"//@componentInstance.1/@featureInstance.2",    "connectionReference" :[ {      "context" :"/",      "source" :"//@componentInstance.1/@featureInstance.2",      "destination" :"//@componentInstance.2/@featureInstance.4",      "connection" :{        "type" :"aadl2:FeatureConnection",        "href" :"../../github/tpAADL/lgs.aadl#/0/@ownedPublicSection/@ownedClassifier.25/@ownedFeatureConnection.1"      }    }, {      "context" :"//@componentInstance.2",      "source" :"//@componentInstance.2/@featureInstance.4",      "destination" :"//@componentInstance.2/@componentInstance.13/@featureInstance.2",      "connection" :{        "type" :"aadl2:FeatureConnection",        "href" :"../../github/tpAADL/lgs.aadl#/0/@ownedPublicSection/@ownedClassifier.49/@ownedFeatureConnection.3"      }    } ]  }, {    "name" :"DigitalPart.ExtendEv -> ElectrovalvesSystem.lgsSystem_ExtendEvSystemImpl.ExtendEv",    "complete" :"true",    "kind" :"portConnection",    "destination" :"//@componentInstance.2/@componentInstance.12/@featureInstance.2",    "source" :"//@componentInstance.1/@featureInstance.3",    "connectionReference" :[ {      "context" :"/",      "source" :"//@componentInstance.1/@featureInstance.3",      "destination" :"//@componentInstance.2/@featureInstance.3",      "connection" :{        "type" :"aadl2:FeatureConnection",        "href" :"../../github/tpAADL/lgs.aadl#/0/@ownedPublicSection/@ownedClassifier.25/@ownedFeatureConnection.0"      }    }, {      "context" :"//@componentInstance.2",      "source" :"//@componentInstance.2/@featureInstance.3",      "destination" :"//@componentInstance.2/@componentInstance.12/@featureInstance.2",      "connection" :{        "type" :"aadl2:FeatureConnection",        "href" :"../../github/tpAADL/lgs.aadl#/0/@ownedPublicSection/@ownedClassifier.49/@ownedFeatureConnection.1"      }    } ]  }, {    "name" :"ElectrovalvesSystem.GenralHydrolicFloww -> GeneralHydrolicFlowBus",    "complete" :"true",    "kind" :"accessConnection",    "destination" :"//@componentInstance.0",    "source" :"//@componentInstance.2/@featureInstance.0",    "connectionReference" :{      "context" :"/",      "source" :"//@componentInstance.2/@featureInstance.0",      "destination" :"//@componentInstance.0",      "connection" :{        "type" :"aadl2:AccessConnection",        "href" :"../../github/tpAADL/lgs.aadl#/0/@ownedPublicSection/@ownedClassifier.25/@ownedAccessConnection.0"      }    }  } ],  "classifier" :{    "type" :"aadl2:SystemImplementation",    "href" :"../../github/tpAADL/lgs.aadl#lgs.lgsSystem.impl"  },  "systemOperationMode" :{    "name" :"No Modes"  },  "componentImplementation" :{    "type" :"aadl2:SystemImplementation",    "href" :"../../github/tpAADL/lgs.aadl#lgs.lgsSystem.impl"  }}